mditre/__init__.py
mditre/convert_mitre_dataset.py
mditre/data.py
mditre/data_utils.py
mditre/models.py
mditre/rule_viz.py
mditre/trainer.py
mditre/utils.py
mditre/visualize.py
mditre-0.1.6.dist-info/LICENSE
mditre-0.1.6.dist-info/METADATA
mditre-0.1.6.dist-info/WHEEL
mditre-0.1.6.dist-info/top_level.txt
mditre-0.1.6.dist-info/RECORD
