Metadata-Version: 2.1
Name: mditre
Version: 0.1.6
Summary: Microbial Differentibale Temporal Rule Engine
Home-page: https://github.com/gerberlab/mditre
Author: Venkata Suhas Maringanti
Author-email: vsuhas.m@gmail.com
License: GPLv3
Platform: UNKNOWN
Classifier: Development Status :: 4 - Beta
Classifier: Intended Audience :: Science/Research
Classifier: License :: OSI Approved :: GNU General Public License (GPL)
Classifier: Topic :: Scientific/Engineering :: Bio-Informatics
Requires-Python: >=3.6
License-File: LICENSE
Requires-Dist: numpy
Requires-Dist: scikit-learn
Requires-Dist: PyQt5 (==5.11.3)
Requires-Dist: ete3
Requires-Dist: matplotlib
Requires-Dist: seaborn
Requires-Dist: pandas
Requires-Dist: scipy
Requires-Dist: dendropy
Requires-Dist: jupyterlab
